[
  {
    "level": "1",
    "hp": "3600",
    "heal/5s": "35",
    "attack": "190",
    "def": "100",
    "sp. attack": "20",
    "sp. def": "80",
    "atk spd": "25%",
    "mv. speed": "3.8m/s",
    "Support energy rate": "0%",
    "lifesteal": "0%",
    "crit chance": "0%",
    "tenacity": "0%",
    "CDR": "0%"
  },
  {
    "level": "2",
    "hp": "3757",
    "heal/5s": "37",
    "attack": "203",
    "def": "112",
    "sp. attack": "23",
    "sp. def": "90",
    "atk spd": "25.53%",
    "mv. speed": "3.8m/s",
    "Support energy rate": "0%",
    "lifesteal": "0%",
    "crit chance": "5%",
    "tenacity": "3.33%",
    "CDR": "0%"
  },
  {
    "level": "3",
    "hp": "3929",
    "heal/5s": "39",
    "attack": "218",
    "def": "125",
    "sp. attack": "27",
    "sp. def": "101",
    "atk spd": "26.12%",
    "mv. speed": "3.8m/s",
    "Support energy rate": "0%",
    "lifesteal": "0%",
    "crit chance": "5%",
    "tenacity": "6.66%",
    "CDR": "0%"
  },
  {
    "level": "4",
    "hp": "4118",
    "heal/5s": "41",
    "attack": "234",
    "def": "140",
    "sp. attack": "31",
    "sp. def": "113",
    "atk spd": "26.77%",
    "mv. speed": "3.8m/s",
    "Support energy rate": "0%",
    "lifesteal": "0%",
    "crit chance": "5%",
    "tenacity": "9.99%",
    "CDR": "0%"
  },
  {
    "level": "5",
    "hp": "4326",
    "heal/5s": "43",
    "attack": "252",
    "def": "156",
    "sp. attack": "35",
    "sp. def": "126",
    "atk spd": "27.48%",
    "mv. speed": "3.95m/s",
    "Support energy rate": "0%",
    "lifesteal": "5%",
    "crit chance": "15%",
    "tenacity": "13.32%",
    "CDR": "0%"
  },
  {
    "level": "6",
    "hp": "4555",
    "heal/5s": "45",
    "attack": "271",
    "def": "174",
    "sp. attack": "40",
    "sp. def": "140",
    "atk spd": "28.26%",
    "mv. speed": "3.95m/s",
    "Support energy rate": "0%",
    "lifesteal": "5%",
    "crit chance": "15%",
    "tenacity": "16.65%",
    "CDR": "0%"
  },
  {
    "level": "7",
    "hp": "4807",
    "heal/5s": "48",
    "attack": "292",
    "def": "193",
    "sp. attack": "45",
    "sp. def": "155",
    "atk spd": "29.12%",
    "mv. speed": "4.1m/s",
    "Support energy rate": "0%",
    "lifesteal": "5%",
    "crit chance": "15%",
    "tenacity": "19.98%",
    "CDR": "0%"
  },
  {
    "level": "8",
    "hp": "5085",
    "heal/5s": "51",
    "attack": "315",
    "def": "214",
    "sp. attack": "51",
    "sp. def": "172",
    "atk spd": "30.07%",
    "mv. speed": "4.1m/s",
    "Support energy rate": "0%",
    "lifesteal": "5%",
    "crit chance": "15%",
    "tenacity": "19.98%",
    "CDR": "0%"
  },
  {
    "level": "9",
    "hp": "5391",
    "heal/5s": "54",
    "attack": "341",
    "def": "238",
    "sp. attack": "58",
    "sp. def": "191",
    "atk spd": "31.11%",
    "mv. speed": "4.25m/s",
    "Support energy rate": "0%",
    "lifesteal": "10%",
    "crit chance": "25%",
    "tenacity": "19.98%",
    "CDR": "0%"
  },
  {
    "level": "10",
    "hp": "5728",
    "heal/5s": "57",
    "attack": "369",
    "def": "264",
    "sp. attack": "65",
    "sp. def": "212",
    "atk spd": "32.26%",
    "mv. speed": "4.25m/s",
    "Support energy rate": "0%",
    "lifesteal": "10%",
    "crit chance": "25%",
    "tenacity": "19.98%",
    "CDR": "0%"
  },
  {
    "level": "11",
    "hp": "6100",
    "heal/5s": "61",
    "attack": "400",
    "def": "293",
    "sp. attack": "73",
    "sp. def": "235",
    "atk spd": "33.53%",
    "mv. speed": "4.4m/s",
    "Support energy rate": "0%",
    "lifesteal": "10%",
    "crit chance": "25%",
    "tenacity": "19.98%",
    "CDR": "0%"
  },
  {
    "level": "12",
    "hp": "6509",
    "heal/5s": "65",
    "attack": "434",
    "def": "325",
    "sp. attack": "82",
    "sp. def": "260",
    "atk spd": "34.92%",
    "mv. speed": "4.4m/s",
    "Support energy rate": "0%",
    "lifesteal": "10%",
    "crit chance": "25%",
    "tenacity": "19.98%",
    "CDR": "0%"
  },
  {
    "level": "13",
    "hp": "6959",
    "heal/5s": "70",
    "attack": "472",
    "def": "360",
    "sp. attack": "92",
    "sp. def": "287",
    "atk spd": "36.45%",
    "mv. speed": "4.4m/s",
    "Support energy rate": "0%",
    "lifesteal": "15%",
    "crit chance": "25%",
    "tenacity": "19.98%",
    "CDR": "0%"
  },
  {
    "level": "14",
    "hp": "7455",
    "heal/5s": "75",
    "attack": "514",
    "def": "398",
    "sp. attack": "103",
    "sp. def": "317",
    "atk spd": "38.14%",
    "mv. speed": "4.4m/s",
    "Support energy rate": "0%",
    "lifesteal": "15%",
    "crit chance": "25%",
    "tenacity": "19.98%",
    "CDR": "0%"
  },
  {
    "level": "15",
    "hp": "8000",
    "heal/5s": "80",
    "attack": "560",
    "def": "440",
    "sp. attack": "115",
    "sp. def": "350",
    "atk spd": "40%",
    "mv. speed": "4.4m/s",
    "Support energy rate": "0%",
    "lifesteal": "15%",
    "crit chance": "25%",
    "tenacity": "19.98%",
    "CDR": "0%"
  }
]
